dcentralab_qa_infra_automation/__init__.py
dcentralab_qa_infra_automation/data/read_data.py
dcentralab_qa_infra_automation/drivers/BraveDriver.py
dcentralab_qa_infra_automation/drivers/ChromeDriver.py
dcentralab_qa_infra_automation/drivers/HelperFunctions.py
dcentralab_qa_infra_automation/fixtures/CreateTargetDirectory.py
dcentralab_qa_infra_automation/fixtures/HtmlReports.py
dcentralab_qa_infra_automation/fixtures/InitGlobalParameters.py
dcentralab_qa_infra_automation/fixtures/Loggers.py
dcentralab_qa_infra_automation/fixtures/OpenSiteWithCRXExtension.py
dcentralab_qa_infra_automation/fixtures/ParameterInjection.py
dcentralab_qa_infra_automation/fixtures/ReportLoggers.py
dcentralab_qa_infra_automation/fixtures/Screenshot.py
dcentralab_qa_infra_automation/fixtures/SetupDriver.py
dcentralab_qa_infra_automation/infra/CustomEventListener.py
dcentralab_qa_infra_automation/pages/BasePage.py
dcentralab_qa_infra_automation/pages/coinbasePages/CoinbaseConfirmPage.py
dcentralab_qa_infra_automation/pages/coinbasePages/CoinbaseConfirmRequestPage.py
dcentralab_qa_infra_automation/pages/coinbasePages/CoinbaseConnectToWebsitePage.py
dcentralab_qa_infra_automation/pages/coinbasePages/CoinbaseCreatePasswordPage.py
dcentralab_qa_infra_automation/pages/coinbasePages/CoinbaseCreateWalletPage.py
dcentralab_qa_infra_automation/pages/coinbasePages/CoinbaseImportWalletPage.py
dcentralab_qa_infra_automation/pages/coinbasePages/CoinbasePortfolioPage.py
dcentralab_qa_infra_automation/pages/coinbasePages/CoinbaseUseAnExistingWalletPage.py
dcentralab_qa_infra_automation/pages/metamaskPages/ConnectWithMetamaskPage.py
dcentralab_qa_infra_automation/pages/metamaskPages/MetamaskConfirmPage.py
dcentralab_qa_infra_automation/pages/metamaskPages/MetamaskCongratulationsPage.py
dcentralab_qa_infra_automation/pages/metamaskPages/MetamaskCreatePasswordPage.py
dcentralab_qa_infra_automation/pages/metamaskPages/MetamaskImportWalletPage.py
dcentralab_qa_infra_automation-2.3.6.dist-info/METADATA
dcentralab_qa_infra_automation-2.3.6.dist-info/WHEEL
dcentralab_qa_infra_automation-2.3.6.dist-info/licenses/LICENSE
dcentralab_qa_infra_automation-2.3.6.dist-info/RECORD
