Metadata-Version: 2.1
Name: dcentralab_qa_infra_automation
Version: 2.3.6
Summary: Selenium Python Framework for DcentraLab Products
Project-URL: Homepage, https://github.com/pypa/sampleproject
Project-URL: Bug Tracker, https://github.com/pypa/sampleproject/issues
Author-email: Efrat Cohen <efrat.cohen@verisoft.co>, David Bouchard Pinto <david.pinto@dcentralab.com>, Sharon Casson <sharon.casson@dcentralab.com>
License-File: LICENSE
Classifier: License :: OSI Approved :: MIT License
Classifier: Operating System :: OS Independent
Classifier: Programming Language :: Python :: 3
Requires-Python: >=3.7
